easy_mock/__about__.py
easy_mock/__init__.py
easy_mock/cli.py
easy_mock/common.py
easy_mock/config.py
easy_mock/core.py
easy_mock/loader.py
easy_mock/process.py
easy_mock/util.py
easy_mock-1.1.dist-info/METADATA
easy_mock-1.1.dist-info/WHEEL
easy_mock-1.1.dist-info/entry_points.txt
easy_mock-1.1.dist-info/top_level.txt
easy_mock-1.1.dist-info/RECORD
