Metadata-Version: 2.1
Name: easy-mock
Version: 1.1
Summary: Generate mock service according to the YAML/JSON file in the current directory
Home-page: UNKNOWN
License: UNKNOWN
Keywords: har converter HttpRunner yaml json
Platform: UNKNOWN
Classifier: Development Status :: 3 - Alpha
Classifier: Programming Language :: Python :: 3.7
Requires-Python: >=3
Requires-Dist: PyYAML
Requires-Dist: jsonschema
Requires-Dist: loguru
Requires-Dist: flask
